gherkin_formatter/__init__.py
gherkin_formatter/formatter.py
gherkin_formatter/parser_writer.py
gherkin_formatter-0.1.2.dist-info/licenses/LICENSE
gherkin_formatter-0.1.2.dist-info/METADATA
gherkin_formatter-0.1.2.dist-info/WHEEL
gherkin_formatter-0.1.2.dist-info/entry_points.txt
gherkin_formatter-0.1.2.dist-info/top_level.txt
gherkin_formatter-0.1.2.dist-info/RECORD
