Metadata-Version: 2.4
Name: gherkin-formatter
Version: 0.1.2
Summary: A command-line tool to format Gherkin .feature files.
Requires-Python: >=3.9
License-File: LICENSE
Requires-Dist: gherkin-official
Requires-Dist: ruamel.yaml>=0.17.21
Provides-Extra: dev
Requires-Dist: black; extra == "dev"
Requires-Dist: isort; extra == "dev"
Requires-Dist: pre-commit; extra == "dev"
Requires-Dist: pyrefly; extra == "dev"
Requires-Dist: pytest; extra == "dev"
Requires-Dist: ruff; extra == "dev"
Dynamic: license-file
